{
  "instructions": {
    "inhale": "/audio/breathwork/inhale.mp3",
    "hold": "/audio/breathwork/hold.mp3",
    "exhale": "/audio/breathwork/exhale.mp3",
    "holdEmpty": "/audio/breathwork/hold-empty.mp3"
  },
  "counting": {
    "1": "/audio/breathwork/count-1.mp3",
    "2": "/audio/breathwork/count-2.mp3",
    "3": "/audio/breathwork/count-3.mp3",
    "4": "/audio/breathwork/count-4.mp3",
    "5": "/audio/breathwork/count-5.mp3",
    "6": "/audio/breathwork/count-6.mp3",
    "7": "/audio/breathwork/count-7.mp3",
    "8": "/audio/breathwork/count-8.mp3",
    "9": "/audio/breathwork/count-9.mp3",
    "10": "/audio/breathwork/count-10.mp3",
    "11": "/audio/breathwork/count-11.mp3",
    "12": "/audio/breathwork/count-12.mp3",
    "13": "/audio/breathwork/count-13.mp3",
    "14": "/audio/breathwork/count-14.mp3",
    "15": "/audio/breathwork/count-15.mp3"
  },
  "session": {
    "start": "/audio/breathwork/session-start.mp3",
    "complete": "/audio/breathwork/session-complete.mp3"
  }
}